dapper_python/__init__.py
dapper_python/dataset_loader.py
dapper_python/normalize.py
dapper_python/databases/database.py
dapper_python/databases/linuxDB.py
dapper_python/databases/nugetDB.py
dapper_python/databases/pythonDB.py
dapper_python-0.0.0.dev3.dist-info/METADATA
dapper_python-0.0.0.dev3.dist-info/WHEEL
dapper_python-0.0.0.dev3.dist-info/top_level.txt
dapper_python-0.0.0.dev3.dist-info/RECORD
