Metadata-Version: 2.4
Name: dapper-python
Version: 0.0.0.dev3
Summary: A Python package for interacting with DAPper datasets
Author-email: Ryan Mast <mast9@llnl.gov>
License: MIT License
Project-URL: Homepage, https://github.com/LLNL/dapper
Project-URL: Discussions, https://github.com/LLNL/dapper/discussions
Project-URL: Issue Tracker, https://github.com/LLNL/dapper/issues
Project-URL: Source Code, https://github.com/LLNL/dapper
Classifier: Programming Language :: Python :: 3
Classifier: License :: OSI Approved :: MIT License
Classifier: Operating System :: OS Independent
Classifier: Intended Audience :: Developers
Classifier: Intended Audience :: Science/Research
Classifier: Topic :: Database
Classifier: Topic :: Security
Classifier: Topic :: Utilities
Requires-Python: >=3.6
Requires-Dist: tomlkit
Requires-Dist: typing-extensions>=4.6; python_version < "3.10"
Provides-Extra: test
Requires-Dist: pytest; extra == "test"
Provides-Extra: dev
Requires-Dist: build; extra == "dev"
Requires-Dist: pre-commit; extra == "dev"
